srtrail/__init__.py
srtrail/imageinfo.py
srtrail/layer.py
srtrail/property.py
srtrail/trail.py
srtrail-0.0.1.dist-info/LICENSE
srtrail-0.0.1.dist-info/METADATA
srtrail-0.0.1.dist-info/WHEEL
srtrail-0.0.1.dist-info/top_level.txt
srtrail-0.0.1.dist-info/RECORD
