Metadata-Version: 2.1
Name: srtrail
Version: 0.0.1
Summary: SpeedRunners trail editing library
Home-page: https://github.com/pop4959/srtrail
Author: pop4959
Author-email: pop4959@gmail.com
License: UNKNOWN
Platform: UNKNOWN
